pybolt/__init__.py
pybolt/pybolt.py
src/pybolt/__init__.py
src/pybolt/pybolt.py
simple_passbolt_client-0.0.2.dist-info/METADATA
simple_passbolt_client-0.0.2.dist-info/WHEEL
simple_passbolt_client-0.0.2.dist-info/top_level.txt
simple_passbolt_client-0.0.2.dist-info/RECORD
