Metadata-Version: 2.1
Name: simple-passbolt-client
Version: 0.0.2
Summary: Simple Python client for passbolt
Home-page: https://github.com/slazzaris/pybolt
Author: Simone Lazzaris
License: Apache License Version 2.0
Keywords: passbolt,gpgauth
Classifier: Intended Audience :: Developers
Classifier: Topic :: Software Development :: Build Tools
Classifier: License :: OSI Approved :: Apache Software License
Classifier: Operating System :: OS Independent
Classifier: Programming Language :: Python :: 3.9
Requires-Python: >=3.9
Requires-Dist: certifi ==2024.2.2
Requires-Dist: cffi ==1.16.0
Requires-Dist: charset-normalizer ==3.3.2
Requires-Dist: cryptography ==42.0.5
Requires-Dist: idna ==3.6
Requires-Dist: PGPy ==0.6.0
Requires-Dist: pyasn1 ==0.5.1
Requires-Dist: pycparser ==2.21
Requires-Dist: requests ==2.31.0
Requires-Dist: urllib3 ==2.2.1
